ptdb/__init__.py
ptdb-0.2.1.dist-info/COPYING
ptdb-0.2.1.dist-info/WHEEL
ptdb-0.2.1.dist-info/METADATA
ptdb-0.2.1.dist-info/RECORD
