Metadata-Version: 2.1
Name: ptdb
Version: 0.2.1
Summary: A pdb class based on ptpython
Home-page: https://github.com/4thel00z/ptdb
License: GPL-3
Author: 4thel00z
Author-email: 4thel00z@gmail.com
Requires-Python: >=3.7,<4.0
Classifier: License :: Other/Proprietary License
Classifier: Programming Language :: Python :: 3
Classifier: Programming Language :: Python :: 3.10
Classifier: Programming Language :: Python :: 3.7
Classifier: Programming Language :: Python :: 3.8
Classifier: Programming Language :: Python :: 3.9
Requires-Dist: ptpython (>=3.0.20,<4.0.0)
